ddtruss/__about__.py
ddtruss/__init__.py
ddtruss/solver.py
ddtruss/truss.py
ddtruss-0.0.3.dist-info/LICENSE
ddtruss-0.0.3.dist-info/METADATA
ddtruss-0.0.3.dist-info/WHEEL
ddtruss-0.0.3.dist-info/top_level.txt
ddtruss-0.0.3.dist-info/RECORD
