Metadata-Version: 2.1
Name: ddtruss
Version: 0.0.3
Summary: Data-driven solver for truss structures
Home-page: https://github.com/tianyikillua/ddtruss
Author: Tianyi Li
Author-email: tianyikillua@gmail.com
License: License :: OSI Approved :: MIT License
Platform: UNKNOWN
Classifier: License :: OSI Approved :: MIT License
Classifier: Development Status :: 4 - Beta
Classifier: Operating System :: OS Independent
Classifier: Programming Language :: Python :: 3
Classifier: Intended Audience :: Science/Research
Classifier: Topic :: Scientific/Engineering
Classifier: Topic :: Scientific/Engineering :: Physics
Requires-Dist: numpy
Requires-Dist: scipy
